instapy2/__init__.py
instapy2/instapy2.py
instapy2/types/__init__.py
instapy2/types/commenttype.py
instapy2/types/liketype.py
instapy2/types/posttype.py
instapy2/utilities/__init__.py
instapy2/utilities/authentication.py
instapy2/utilities/comments.py
instapy2/utilities/limitations.py
instapy2/utilities/logger.py
instapy2/utilities/medias.py
instapy2/utilities/persistence.py
instapy2/utilities/utility.py
instapy2-0.0.28.dist-info/LICENSE.md
instapy2-0.0.28.dist-info/METADATA
instapy2-0.0.28.dist-info/WHEEL
instapy2-0.0.28.dist-info/top_level.txt
instapy2-0.0.28.dist-info/RECORD
