Metadata-Version: 2.1
Name: instapy2
Version: 0.0.28
Summary: Automation script for Instagram that farms comments, follows and likes.
Home-page: https://github.com/InstaPy2/InstaPy2
Author: Antique
Author-email: official.antique@gmail.com
Keywords: automation,bot,ig,insta,instagram,instagrapi,instapy,instapy2,python,python3
Classifier: Development Status :: 4 - Beta
Classifier: Environment :: Console
Classifier: Intended Audience :: Developers
Classifier: Intended Audience :: End Users/Desktop
Classifier: License :: OSI Approved :: GNU General Public License v3 (GPLv3)
Classifier: Natural Language :: English
Classifier: Operating System :: MacOS
Classifier: Operating System :: Microsoft :: Windows
Classifier: Operating System :: POSIX
Classifier: Programming Language :: Python
Classifier: Topic :: Software Development
Classifier: Topic :: Utilities
License-File: LICENSE.md
Requires-Dist: emoji
Requires-Dist: instagrapi
Requires-Dist: Pillow
Requires-Dist: python-dotenv
